hf_model_s_cpu/__init__.py
hf_model_s_cpu/model_s.py
hf_model_s_cpu/model_s.py-
hf_model_s_cpu-0.1.1.dist-info/LICENSE
hf_model_s_cpu-0.1.1.dist-info/WHEEL
hf_model_s_cpu-0.1.1.dist-info/METADATA
hf_model_s_cpu-0.1.1.dist-info/RECORD
