Metadata-Version: 2.1
Name: hf-model-s-cpu
Version: 0.1.1
Summary: model-s served from hf spaces using torch+cpu
Home-page: https://github.com/ffreemt/model-s
License: MIT
Author: ffreemt
Requires-Python: >=3.8.3,<4.0.0
Classifier: License :: OSI Approved :: MIT License
Classifier: Programming Language :: Python :: 3
Classifier: Programming Language :: Python :: 3.10
Classifier: Programming Language :: Python :: 3.9
Requires-Dist: Pillow (>=9.1.0,<10.0.0)
Requires-Dist: alive-progress (>=2.4.1,<3.0.0)
Requires-Dist: huggingface-hub (>=0.5.1,<0.6.0)
Requires-Dist: install (>=1.3.5,<2.0.0)
Requires-Dist: joblib (>=1.1.0,<2.0.0)
Requires-Dist: logzero (>=1.7.0,<2.0.0)
Requires-Dist: nltk (>=3.7,<4.0)
Requires-Dist: numpy (>=1.22.3,<2.0.0)
Requires-Dist: scikit-learn (>=1.0.2,<2.0.0)
Requires-Dist: sentencepiece (>=0.1.96,<0.2.0)
Requires-Dist: tqdm (>=4.64.0,<5.0.0)
Requires-Dist: transformers (>=4.18.0,<5.0.0)
Project-URL: Repository, https://github.com/ffreemt/model-s
